apibean/__init__.py
apibean/client/__init__.py
apibean/client/engine/__init__.py
apibean/client/engine/_agent.py
apibean/client/engine/_config.py
apibean/client/engine/_consts.py
apibean/client/engine/_curli.py
apibean/client/engine/_decorators.py
apibean/client/engine/_errors.py
apibean/client/engine/_helpers.py
apibean/client/engine/_print.py
apibean/client/engine/_store.py
apibean/client/engine/_tools.py
apibean/client/engine/_utils.py
apibean_client-0.1.0.dist-info/licenses/LICENSE.txt
apibean_client-0.1.0.dist-info/METADATA
apibean_client-0.1.0.dist-info/WHEEL
apibean_client-0.1.0.dist-info/top_level.txt
apibean_client-0.1.0.dist-info/RECORD
