Metadata-Version: 2.4
Name: apibean-client
Version: 0.1.0
Author: skelethon
License-Expression: GPL-3.0
Keywords: restful-client
Requires-Python: <4.0,>=3.9
License-File: LICENSE.txt
Requires-Dist: httpx<1.0.0,>=0.25.1
Requires-Dist: pyyaml>=6.0.2
Dynamic: license-file
